Metadata-Version: 2.1
Name: tabulate-slip39
Version: 0.10.3
Summary: Pretty-print tabular data
Author-email: Sergey Astanin <s.astanin@gmail.com>
License: MIT
Project-URL: Homepage, https://github.com/pjkundert/python-tabulate
Classifier: Development Status :: 4 - Beta
Classifier: License :: OSI Approved :: MIT License
Classifier: Operating System :: OS Independent
Classifier: Programming Language :: Python :: 3
Classifier: Programming Language :: Python :: 3.9
Classifier: Programming Language :: Python :: 3.10
Classifier: Programming Language :: Python :: 3.11
Classifier: Programming Language :: Python :: 3.12
Classifier: Programming Language :: Python :: 3.13
Classifier: Topic :: Software Development :: Libraries
Requires-Python: >=3.9
License-File: LICENSE
Provides-Extra: widechars
Requires-Dist: wcwidth; extra == "widechars"
